livestyled/__init__.py
livestyled/client.py
livestyled/resource_client.py
livestyled/utils.py
livestyled/models/__init__.py
livestyled/models/app.py
livestyled/models/audience.py
livestyled/models/audience_device.py
livestyled/models/booking.py
livestyled/models/cohort.py
livestyled/models/competition.py
livestyled/models/device.py
livestyled/models/device_consent.py
livestyled/models/device_preference.py
livestyled/models/device_push_consent.py
livestyled/models/device_reality.py
livestyled/models/device_token.py
livestyled/models/event.py
livestyled/models/event_category.py
livestyled/models/event_date.py
livestyled/models/event_stage.py
livestyled/models/fixture.py
livestyled/models/fulfilment_point.py
livestyled/models/league_table.py
livestyled/models/location.py
livestyled/models/magic_field.py
livestyled/models/news.py
livestyled/models/order.py
livestyled/models/product.py
livestyled/models/push_broadcast.py
livestyled/models/push_consent.py
livestyled/models/reality.py
livestyled/models/season.py
livestyled/models/sport_venue.py
livestyled/models/team.py
livestyled/models/ticket.py
livestyled/models/ticket_auth.py
livestyled/models/ticket_integration.py
livestyled/models/user.py
livestyled/models/venue.py
livestyled/models/tests/__init__.py
livestyled/models/tests/test_fixture.py
livestyled/models/tests/test_order.py
livestyled/models/tests/test_team.py
livestyled/schemas/__init__.py
livestyled/schemas/app.py
livestyled/schemas/audience.py
livestyled/schemas/audience_device.py
livestyled/schemas/booking.py
livestyled/schemas/cohort.py
livestyled/schemas/competition.py
livestyled/schemas/device.py
livestyled/schemas/device_consent.py
livestyled/schemas/device_preference.py
livestyled/schemas/device_reality.py
livestyled/schemas/device_token.py
livestyled/schemas/event.py
livestyled/schemas/event_category.py
livestyled/schemas/event_integration.py
livestyled/schemas/event_stage.py
livestyled/schemas/fields.py
livestyled/schemas/fixture.py
livestyled-1.1.1.dist-info/LICENSE
livestyled-1.1.1.dist-info/METADATA
livestyled-1.1.1.dist-info/WHEEL
livestyled-1.1.1.dist-info/entry_points.txt
livestyled-1.1.1.dist-info/top_level.txt
livestyled-1.1.1.dist-info/RECORD
