Metadata-Version: 2.1
Name: livestyled
Version: 1.1.1
Summary: UNKNOWN
Home-page: https://github.com/livestyled/python-sdk
Author: LiveStyled
Author-email: dev@livestyled.com
License: UNKNOWN
Platform: UNKNOWN
Requires-Dist: marshmallow (==3.3.0)
Requires-Dist: marshmallow-polyfield (==5.7)
Requires-Dist: pytz
Requires-Dist: requests (==2.22.0)
